bytefields/Bits.py
bytefields/__init__.py
bytefields-0.0.1.dist-info/METADATA
bytefields-0.0.1.dist-info/WHEEL
bytefields-0.0.1.dist-info/top_level.txt
bytefields-0.0.1.dist-info/RECORD
