Metadata-Version: 2.1
Name: bytefields
Version: 0.0.1
Summary: Python byte field manipulation
Home-page: UNKNOWN
Author: Zach Morris
Author-email: zacharymorr@outlook.com
License: UNKNOWN
Platform: UNKNOWN
